main.py
webcrawlergithub-0.1.0.dist-info/METADATA
webcrawlergithub-0.1.0.dist-info/WHEEL
webcrawlergithub-0.1.0.dist-info/entry_points.txt
webcrawlergithub-0.1.0.dist-info/top_level.txt
webcrawlergithub-0.1.0.dist-info/RECORD
